lean_dojo_v2/__init__.py
lean_dojo_v2/agent/__init__.py
lean_dojo_v2/agent/base_agent.py
lean_dojo_v2/agent/external_agent.py
lean_dojo_v2/agent/hf_agent.py
lean_dojo_v2/agent/lean_agent.py
lean_dojo_v2/external_api/ExternalAPI.lean
lean_dojo_v2/external_api/LeanCopilot.lean
lean_dojo_v2/external_api/lakefile.lean
lean_dojo_v2/external_api/LeanCopilot/Frontend.lean
lean_dojo_v2/external_api/LeanCopilot/Models.lean
lean_dojo_v2/external_api/LeanCopilot/Tactics.lean
lean_dojo_v2/external_api/LeanCopilot/Models/External.lean
lean_dojo_v2/external_api/LeanCopilot/Models/Interface.lean
lean_dojo_v2/external_api/python/models.py
lean_dojo_v2/external_api/python/server.py
lean_dojo_v2/external_api/python/external_models/__init__.py
lean_dojo_v2/external_api/python/external_models/claude_runner.py
lean_dojo_v2/external_api/python/external_models/external_parser.py
lean_dojo_v2/external_api/python/external_models/gemini_runner.py
lean_dojo_v2/external_api/python/external_models/hf_runner.py
lean_dojo_v2/external_api/python/external_models/oai_runner.py
lean_dojo_v2/external_api/python/external_models/vllm_runner.py
lean_dojo_v2/lean_agent/__init__.py
lean_dojo_v2/lean_agent/__main__.py
lean_dojo_v2/lean_agent/common.py
lean_dojo_v2/lean_agent/config.py
lean_dojo_v2/lean_agent/database/__init__.py
lean_dojo_v2/lean_agent/database/dynamic_database.py
lean_dojo_v2/lean_agent/database/models/__init__.py
lean_dojo_v2/lean_agent/database/models/annotations.py
lean_dojo_v2/lean_agent/database/models/premises.py
lean_dojo_v2/lean_agent/database/models/repository.py
lean_dojo_v2/lean_agent/database/models/theorems.py
lean_dojo_v2/lean_agent/generator/__init__.py
lean_dojo_v2/lean_agent/generator/datamodule.py
lean_dojo_v2/lean_agent/generator/main.py
lean_dojo_v2/lean_agent/generator/model.py
lean_dojo_v2/lean_agent/generator/confs/cli_lean4_random.yaml
lean_dojo_v2/lean_agent/prover/__init__.py
lean_dojo_v2/lean_agent/prover/proof_search.py
lean_dojo_v2-1.0.1.dist-info/licenses/LICENSE
lean_dojo_v2-1.0.1.dist-info/METADATA
lean_dojo_v2-1.0.1.dist-info/WHEEL
lean_dojo_v2-1.0.1.dist-info/top_level.txt
lean_dojo_v2-1.0.1.dist-info/RECORD
